zagen/__init__.py
zagen/py.typed
zagen/agent/__init__.py
zagen/agent/openai.py
zagen/agent/types.py
zagen/dsl/__init__.py
zagen/mcp/__init__.py
zagen/mcp/client.py
zagen/mcp/server.py
zagen/mcp/utils.py
zagen/types/__init__.py
zagen/types/message.py
zagen-0.1.2.dist-info/METADATA
zagen-0.1.2.dist-info/WHEEL
zagen-0.1.2.dist-info/RECORD
